{"id":"899","post_title":"Ferme de Thierry Angelot","post_content":"","_order":"0","_date":"2024-06-17 09:56:54","featured_image":{"url":"https:\/\/rsfp.localhost\/wp-content\/uploads\/2024\/06\/recolte-des-carottes-pdf-scaled.jpg","base64":{"r16_9":"11c18af5f9608c12da276ebb549b0838-r16_9","r1920_1080":"11c18af5f9608c12da276ebb549b0838-r1920_1080","r4_3":"11c18af5f9608c12da276ebb549b0838-r4_3","r10_6":"11c18af5f9608c12da276ebb549b0838-r10_6","r155_148":"11c18af5f9608c12da276ebb549b0838-r155_148"}},"farm_in_transmission":"","farm_to_transmit":"","general_address":"a:1:{i:0;a:4:{s:13:\"address_line1\";s:17:\"8 rue de l\u2019orne\";s:13:\"address_line2\";s:0:\"\";s:16:\"postal_code_city\";s:23:\"52190 Choilley-Dardenay\";s:7:\"country\";s:0:\"\";}}","general_biography":"","eneral_emails":["thierry.angelot@orange.fr"],"general_farmers":["Thierry ANGELOT"],"general_gallery":"","general_legal_entity":"","general_links":"","general_phones":["06 56 71 08 03"],"geolocation_address":"Choilley, Choilley-Dardenay, Langres, Haute-Marne, Grand Est, France m\u00e9tropolitaine, 52190, France","geolocation_lat":"47.6695582","geolocation_lng":"5.367924555663883","geolocation_map":"47.6695582,5.3679245556639,14","":"","more_testimony":"\u00ab C'est aussi une philosophie de pouvoir conserver des vari\u00e9t\u00e9s paysannes. \u00bb","transmission_farm_in_transmission":"0","permalink":"https:\/\/rsfp.localhost\/farm\/899\/"}